LICENSE.txt
README.md
awesome_minio/__init__.py
awesome_minio/minio.py
awesome_minio-1.0.3.dist-info/LICENSE.txt
awesome_minio-1.0.3.dist-info/WHEEL
awesome_minio-1.0.3.dist-info/METADATA
awesome_minio-1.0.3.dist-info/RECORD
